odoo/addons/survey_certification_branding/README.rst
odoo/addons/survey_certification_branding/__init__.py
odoo/addons/survey_certification_branding/__manifest__.py
odoo/addons/survey_certification_branding/i18n/es.po
odoo/addons/survey_certification_branding/i18n/it.po
odoo/addons/survey_certification_branding/i18n/survey_certification_branding.pot
odoo/addons/survey_certification_branding/models/__init__.py
odoo/addons/survey_certification_branding/models/survey_survey.py
odoo/addons/survey_certification_branding/readme/CONTRIBUTORS.md
odoo/addons/survey_certification_branding/readme/DESCRIPTION.md
odoo/addons/survey_certification_branding/readme/USAGE.md
odoo/addons/survey_certification_branding/report/survey_report_templates.xml
odoo/addons/survey_certification_branding/static/description/certification_branding_section.png
odoo/addons/survey_certification_branding/static/description/icon.png
odoo/addons/survey_certification_branding/static/description/index.html
odoo/addons/survey_certification_branding/tests/__init__.py
odoo/addons/survey_certification_branding/tests/test_survey_certification_branding.py
odoo/addons/survey_certification_branding/views/survey_survey_views.xml
odoo_addon_survey_certification_branding-16.0.1.0.0.4.dist-info/METADATA
odoo_addon_survey_certification_branding-16.0.1.0.0.4.dist-info/WHEEL
odoo_addon_survey_certification_branding-16.0.1.0.0.4.dist-info/top_level.txt
odoo_addon_survey_certification_branding-16.0.1.0.0.4.dist-info/RECORD
