Metadata-Version: 2.1
Name: odoo-addon-survey_certification_branding
Version: 16.0.1.0.0.4
Summary: This module enables customization of certification reports by allowing a custom logo and company name per certification.
Home-page: https://github.com/OCA/survey
Author: Binhex,Odoo Community Association (OCA)
Author-email: support@odoo-community.org
License: AGPL-3
Classifier: Programming Language :: Python
Classifier: Framework :: Odoo
Classifier: Framework :: Odoo :: 16.0
Classifier: License :: OSI Approved :: GNU Affero General Public License v3
Requires-Python: >=3.10
Requires-Dist: odoo<16.1dev,>=16.0a
